.gitignore
.gitmodules
.travis.yml
HISTORY.md
MANIFEST.in
README.md
TODO.md
setup.py
setup_long_description.rst
test_molt.py
tox.ini
images/molt.png
molt/__init__.py
molt/argprocessor.py
molt/commandline.py
molt/constants.py
molt/defaults.py
molt/dirutil.py
molt/logconfig.py
molt/main.py
molt/molter.py
molt/projectmap.py
molt/visualizer.py
molt.egg-info/PKG-INFO
molt.egg-info/SOURCES.txt
molt.egg-info/dependency_links.txt
molt.egg-info/entry_points.txt
molt.egg-info/requires.txt
molt.egg-info/top_level.txt
molt/commands/__init__.py
molt/commands/molt.py
molt/common/__init__.py
molt/common/equality.py
molt/common/error.py
molt/common/io.py
molt/common/optionparser.py
molt/common/popen.py
molt/demo/sample.json
molt/demo/expected/hello.py
molt/demo/expected/hello/__init__.py
molt/demo/expected/hello/main.py
molt/demo/expected/templates/hello.mustache
molt/demo/lambdas/hash_comment.sh
molt/demo/lambdas/now.sh
molt/demo/partials/copyright.mustache
molt/demo/partials/header.mustache
molt/demo/structure/{{project}}.py.mustache
molt/demo/structure/templates/{{project}}.skip.mustache
molt/demo/structure/{{project}}/__init__.py
molt/demo/structure/{{project}}/main.py.mustache
molt/test/__init__.py
molt/test/dirutil_test.py
molt/test/main_test.py
molt/test/molter_test.py
molt/test/common/__init__.py
molt/test/common/equality_test.py
molt/test/common/popen_test.py
molt/test/data/lambdas/echo_foo.sh
molt/test/data/lambdas/hash_comment.sh
molt/test/extra/__init__.py
molt/test/extra/demo_test.py
molt/test/extra/endtoend_test.py
molt/test/extra/groome_test.py
molt/test/harness/__init__.py
molt/test/harness/alltest.py
molt/test/harness/common.py
molt/test/harness/defaults.py
molt/test/harness/dirmixin.py
molt/test/harness/loading.py
molt/test/harness/main.py
molt/test/harness/sandbox.py
molt/test/harness/templatetest.py
molt_setup/__init__.py
molt_setup/main.py
molt_setup/test/__init__.py
molt_setup/test/main_test.py
molt_setup/test/data/package_dir/foo/foo.txt
molt_setup/test/data/package_dir/foo/bar/foo.txt