Metadata-Version: 1.1
Name: molt
Version: 0.1.0
Summary: Mustache project templates using Python and Groome
Home-page: http://cjerdonek.github.com/molt/
Author: Chris Jerdonek
Author-email: chris.jerdonek@gmail.com
License: UNKNOWN
Keywords: project template mustache pystache groome
Platform: UNKNOWN
Classifier: Development Status :: 4 - Beta
Classifier: License :: OSI Approved :: BSD License
Classifier: Programming Language :: Python
Classifier: Programming Language :: Python :: 2
Classifier: Programming Language :: Python :: 2.7
Classifier: Programming Language :: Python :: Implementation :: PyPy
